{
"type": "FeatureCollection",
"name": "states_centroids",
"crs": { "type": "name", "properties": { "name": "urn:ogc:def:crs:OGC:1.3:CRS84" } },
"features": [
{ "type": "Feature", "properties": { "STUSPS": "CA", "NAME": "California" }, "geometry": { "type": "Point", "coordinates": [ -122.229637648356061, 40.855794245388928 ] } },
{ "type": "Feature", "properties": { "STUSPS": "OR", "NAME": "Oregon" }, "geometry": { "type": "Point", "coordinates": [ -121.289737126193174, 44.009707347214643 ] } },
{ "type": "Feature", "properties": { "STUSPS": "WA", "NAME": "Washington" }, "geometry": { "type": "Point", "coordinates": [ -120.592899874713652, 47.411639218653256 ] } }
]
}
